daopy/__init__.py
daopy/dao.py
daopy/model.py
daopy/utils.py
daopy-0.0.1.dist-info/LICENSE
daopy-0.0.1.dist-info/METADATA
daopy-0.0.1.dist-info/WHEEL
daopy-0.0.1.dist-info/top_level.txt
daopy-0.0.1.dist-info/RECORD
